py_dyt/__init__.py
py_dyt/translate.py
py_dyt-0.1.0.dist-info/LICENSE
py_dyt-0.1.0.dist-info/METADATA
py_dyt-0.1.0.dist-info/WHEEL
py_dyt-0.1.0.dist-info/top_level.txt
py_dyt-0.1.0.dist-info/RECORD
